pytest_timestamper/__init__.py
pytest_timestamper/_version.py
pytest_timestamper/plugin.py
pytest_timestamper-0.0.10.dist-info/LICENSE
pytest_timestamper-0.0.10.dist-info/METADATA
pytest_timestamper-0.0.10.dist-info/WHEEL
pytest_timestamper-0.0.10.dist-info/entry_points.txt
pytest_timestamper-0.0.10.dist-info/top_level.txt
pytest_timestamper-0.0.10.dist-info/RECORD
