Metadata-Version: 2.1
Name: pytest-timestamper
Version: 0.0.10
Summary: Pytest plugin to add a timestamp prefix to the pytest output
Home-page: https://github.com/mbkroese/pytest-timestamper
Classifier: Framework :: Pytest
Classifier: Programming Language :: Python :: 3
Classifier: Programming Language :: Python :: 3.6
Classifier: Programming Language :: Python :: 3.7
Classifier: Programming Language :: Python :: 3.8
Classifier: Programming Language :: Python :: 3.9
License-File: LICENSE
